datakorea/__init__.py
datakorea/version_info.py
datakorea/gerrit/__init__.py
datakorea/gerrit/gerritapi_manager.py
datakorea/kakao/__init__.py
datakorea/kakao/kakaoapi.py
datakorea-0.1.6.dist-info/LICENSE
datakorea-0.1.6.dist-info/METADATA
datakorea-0.1.6.dist-info/WHEEL
datakorea-0.1.6.dist-info/top_level.txt
datakorea-0.1.6.dist-info/RECORD
