Metadata-Version: 2.1
Name: datakorea
Version: 0.1.6
Summary: Korea Rest API data library
Home-page: https://github.com/kukjinman/datakorea
Author: 정국진(Kukjin Chung)
Author-email: kukjinman@gmail.com
License: MIT
Keywords: data,datakorea,restapi,python
Classifier: Programming Language :: Python :: 3
License-File: LICENSE
Requires-Dist: requests
Requires-Dist: selenium
